qcware/forge/__init__.py
qcware/forge/api_calls/__init__.py
qcware/forge/api_calls/api_call.py
qcware/forge/api_calls/api_call_decorator.py
qcware/forge/async_request.py
qcware/forge/circuits/__init__.py
qcware/forge/circuits/api/__init__.py
qcware/forge/circuits/api/run_backend_method.py
qcware/forge/circuits/quasar_backend.py
qcware/forge/config/__init__.py
qcware/forge/config/api_semver.py
qcware/forge/config/config.py
qcware/forge/exceptions.py
qcware/forge/montecarlo/__init__.py
qcware/forge/montecarlo/api/__init__.py
qcware/forge/montecarlo/nisqAE/__init__.py
qcware/forge/montecarlo/nisqAE/api/__init__.py
qcware/forge/montecarlo/nisqAE/api/compute_mle.py
qcware/forge/montecarlo/nisqAE/api/make_schedule.py
qcware/forge/montecarlo/nisqAE/api/run_schedule.py
qcware/forge/montecarlo/nisqAE/api/run_unary.py
qcware/forge/optimization/__init__.py
qcware/forge/optimization/api/__init__.py
qcware/forge/optimization/api/brute_force_minimize.py
qcware/forge/optimization/api/find_optimal_qaoa_angles.py
qcware/forge/optimization/api/optimize_binary.py
qcware/forge/optimization/api/qaoa_expectation_value.py
qcware/forge/optimization/api/qaoa_sample.py
qcware/forge/py.typed
qcware/forge/qio/__init__.py
qcware/forge/qio/api/__init__.py
qcware/forge/qio/api/loader.py
qcware/forge/qml/__init__.py
qcware/forge/qml/api/__init__.py
qcware/forge/qml/api/fit.py
qcware/forge/qml/api/fit_and_predict.py
qcware/forge/qml/api/predict.py
qcware/forge/qml/types/__init__.py
qcware/forge/qutils/__init__.py
qcware/forge/qutils/api/__init__.py
qcware/forge/qutils/api/calculate_nisqAE_MLE.py
qcware/forge/qutils/api/create_qdot_circuit.py
qcware/forge/qutils/api/make_nisqAE_schedule.py
qcware/forge/qutils/api/qdist.py
qcware/forge/qutils/api/qdot.py
qcware/forge/qutils/api/run_nisqAE_schedule.py
qcware/forge/qutils/api/run_nisqAE_unary.py
qcware/forge/request.py
qcware/forge/test/__init__.py
qcware/forge/test/api/__init__.py
qcware/forge/test/api/echo.py
qcware/serialization/__init__.py
qcware-7.4.3.dist-info/LICENSE.txt
qcware-7.4.3.dist-info/WHEEL
qcware-7.4.3.dist-info/METADATA
qcware-7.4.3.dist-info/RECORD
