Metadata-Version: 2.1
Name: qcware
Version: 7.4.3
Summary: The python client for QC Ware's Forge SaaS quantum computing product
Home-page: http://github.com/qcware/platform_client_library_python
Keywords: quantum,computing,cloud,API
Author: Vic Putz
Author-email: vic.putz@qcware.com
Requires-Python: >=3.7,<3.11
Classifier: License :: OSI Approved :: Apache Software License
Classifier: Operating System :: OS Independent
Classifier: Programming Language :: Python :: 3
Classifier: Programming Language :: Python :: 3.10
Classifier: Programming Language :: Python :: 3.7
Classifier: Programming Language :: Python :: 3.8
Classifier: Programming Language :: Python :: 3.9
Requires-Dist: aiohttp (>=3.7.4.post0)
Requires-Dist: backoff (>=1.10.0)
Requires-Dist: colorama (>=0.4.4)
Requires-Dist: icontract (>=2.5.3)
Requires-Dist: lz4 (>=3.1.3)
Requires-Dist: networkx (>=2.5.1)
Requires-Dist: numpy (>=1.21.5,<2.0.0)
Requires-Dist: packaging (>=20.9)
Requires-Dist: pydantic (>=1.8.2)
Requires-Dist: python-decouple (>=3.4)
Requires-Dist: qcware-quasar (>=1.0.4)
Requires-Dist: qubovert (>=1.2.3)
Requires-Dist: requests (>=2.25.1)
Requires-Dist: rich (>=12.0)
Requires-Dist: setuptools (>=57.1.0)
Requires-Dist: tabulate (>=0.8.9)
Requires-Dist: toolz (>=0.11.2)
Project-URL: Documentation, http://qcware.readthedocs.io/en/stable
Project-URL: Repository, http://github.com/qcware/platform_client_library_python
